koneko/__init__.py
koneko/__main__.py
koneko/api.py
koneko/assistants.py
koneko/cli.py
koneko/colors.py
koneko/config.py
koneko/data.py
koneko/download.py
koneko/files.py
koneko/lscat.py
koneko/lscat_app.py
koneko/lscat_prompt.py
koneko/main.py
koneko/picker.py
koneko/printer.py
koneko/prompt.py
koneko/pure.py
koneko/screens.py
koneko/ui.py
koneko/utils.py
koneko/url_login/__init__.py
koneko/url_login/main.py
koneko/url_login/open_login_link.py
koneko/url_login/script.py
koneko-0.13.0.dist-info/LICENSE
koneko-0.13.0.dist-info/METADATA
koneko-0.13.0.dist-info/WHEEL
koneko-0.13.0.dist-info/entry_points.txt
koneko-0.13.0.dist-info/top_level.txt
koneko-0.13.0.dist-info/RECORD
