Metadata-Version: 2.1
Name: koneko
Version: 0.13.0
Summary: Browse pixiv in the terminal
Home-page: https://github.com/akazukin5151/koneko
Author: akazukin5151
License: GPLv3
Project-URL: Source Code, https://github.com/akazukin5151/koneko
Project-URL: Documentation, https://koneko.readthedocs.io/en/latest/
Classifier: License :: OSI Approved :: GNU General Public License v3 or later (GPLv3+)
Classifier: Programming Language :: Python :: 3
Classifier: Operating System :: POSIX :: Linux
Classifier: Operating System :: MacOS
Classifier: Environment :: Console
License-File: LICENSE
Requires-Dist: PixivPy (~=3.7)
Requires-Dist: pixcat (~=0.1)
Requires-Dist: docopt (~=0.6)
Requires-Dist: blessed (~=1.19)
Requires-Dist: pick (~=1.6)
Requires-Dist: funcy (~=1.17)
Requires-Dist: returns (==0.19.0)
Requires-Dist: placeholder (~=1.4)
Requires-Dist: plyer (~=2.1.0)
Requires-Dist: pytest (~=7.2)
